sympy12/__init__.py
sympy1000-0.1.dist-info/METADATA
sympy1000-0.1.dist-info/WHEEL
sympy1000-0.1.dist-info/top_level.txt
sympy1000-0.1.dist-info/RECORD
