Metadata-Version: 2.1
Name: sympy1000
Version: 0.1
Summary: <Basic desc>
Author: <author’s name
Author-email: rakalyanram@gmail.com
Classifier: Programming Language :: Python :: 3
Classifier: License :: OSI Approved :: MIT License
Classifier: Operating System :: OS Independent
